pytest_setupinfo/__init__.py
pytest_setupinfo/pytest_setupinfo.py
pytest_setupinfo-0.1.1.dist-info/entry_points.txt
pytest_setupinfo-0.1.1.dist-info/LICENSE
pytest_setupinfo-0.1.1.dist-info/METADATA
pytest_setupinfo-0.1.1.dist-info/WHEEL
pytest_setupinfo-0.1.1.dist-info/RECORD
