Metadata-Version: 2.1
Name: pytest-setupinfo
Version: 0.1.1
Summary: Displaying setup info during pytest command run
License: MIT
Author: Maheshwar Bolewar
Requires-Python: >=3.10,<4.0
Classifier: License :: OSI Approved :: MIT License
Classifier: Programming Language :: Python :: 3
Classifier: Programming Language :: Python :: 3.10
Classifier: Programming Language :: Python :: 3.11
Requires-Dist: pytest-cov (>=4.0.0,<5.0.0)
